pyleecan/__init__.py
pyleecan/__main__.py
pyleecan/default_config_dict.py
pyleecan/definitions.py
pyleecan/loggers.py
pyleecan/run_GUI.py
pyleecan/Classes/Arc.py
pyleecan/Classes/Arc1.py
pyleecan/Classes/Arc2.py
pyleecan/Classes/Arc3.py
pyleecan/Classes/Bore.py
pyleecan/Classes/BoreFlower.py
pyleecan/Classes/CellMat.py
pyleecan/Classes/Circle.py
pyleecan/Classes/Class_Dict.json
pyleecan/Classes/CondType11.py
pyleecan/Classes/CondType12.py
pyleecan/Classes/CondType21.py
pyleecan/Classes/CondType22.py
pyleecan/Classes/Conductor.py
pyleecan/Classes/DXFImport.py
pyleecan/Classes/DataKeeper.py
pyleecan/Classes/Drive.py
pyleecan/Classes/DriveWave.py
pyleecan/Classes/EEC.py
pyleecan/Classes/EEC_PMSM.py
pyleecan/Classes/EEC_SCIM.py
pyleecan/Classes/Electrical.py
pyleecan/Classes/FPGNSeg.py
pyleecan/Classes/FPGNTri.py
pyleecan/Classes/FluxLink.py
pyleecan/Classes/FluxLinkFEMM.py
pyleecan/Classes/Force.py
pyleecan/Classes/ForceMT.py
pyleecan/Classes/Frame.py
pyleecan/Classes/GUIOption.py
pyleecan/Classes/GaussPoint.py
pyleecan/Classes/Hole.py
pyleecan/Classes/HoleM50.py
pyleecan/Classes/HoleM51.py
pyleecan/Classes/HoleM52.py
pyleecan/Classes/HoleM53.py
pyleecan/Classes/HoleM54.py
pyleecan/Classes/HoleM57.py
pyleecan/Classes/HoleM58.py
pyleecan/Classes/HoleMag.py
pyleecan/Classes/HoleUD.py
pyleecan/Classes/Import.py
pyleecan/Classes/ImportData.py
pyleecan/Classes/ImportGenMatrixSin.py
pyleecan/Classes/ImportGenToothSaw.py
pyleecan/Classes/ImportGenVectLin.py
pyleecan/Classes/ImportGenVectSin.py
pyleecan/Classes/ImportMatlab.py
pyleecan/Classes/ImportMatrix.py
pyleecan/Classes/ImportMatrixVal.py
pyleecan/Classes/ImportMatrixXls.py
pyleecan/Classes/ImportVectorField.py
pyleecan/Classes/IndMag.py
pyleecan/Classes/IndMagFEMM.py
pyleecan/Classes/Input.py
pyleecan/Classes/InputCurrent.py
pyleecan/Classes/InputElec.py
pyleecan/Classes/InputFlux.py
pyleecan/Classes/InputForce.py
pyleecan/Classes/Interpolation.py
pyleecan/Classes/LamHole.py
pyleecan/Classes/LamSlot.py
pyleecan-1.0.1b2.dist-info/LICENSE
pyleecan-1.0.1b2.dist-info/METADATA
pyleecan-1.0.1b2.dist-info/WHEEL
pyleecan-1.0.1b2.dist-info/top_level.txt
pyleecan-1.0.1b2.dist-info/RECORD
