Metadata-Version: 2.1
Name: pyleecan
Version: 1.0.1b2
Summary: Python Library for Electrical Engineering Computational Analysis
Home-page: https://github.com/Eomys/pyleecan
Author: Pyleecan Developers
Author-email: pyleecan@framalistes.org
License: UNKNOWN
Download-URL: https://github.com/Eomys/pyleecan/SciDataTool/archive/1.0.1b2.tar.gz
Platform: UNKNOWN
Classifier: Programming Language :: Python :: 3
Classifier: License :: OSI Approved :: Apache Software License
Classifier: Operating System :: OS Independent
Requires-Python: >= 3.6
Requires-Dist: setuptools
Requires-Dist: cloudpickle (>=1.3.0)
Requires-Dist: matplotlib (>=3.2.1)
Requires-Dist: numpy (>=1.18.2)
Requires-Dist: pandas (>=1.0.3)
Requires-Dist: PySide2 (>=5.15.1)
Requires-Dist: scipy (>=1.4.1)
Requires-Dist: xlrd (>=1.2.0)
Requires-Dist: deap (>=1.3.1)
Requires-Dist: SciDataTool (>=1.1.4)
Requires-Dist: pyvista (>=0.25.3)
Requires-Dist: meshio (>=4.0.15)
Requires-Dist: h5py (>=2.10.0)
Requires-Dist: pyfemm (>=0.1.1) ; platform_system == "Windows"
Provides-Extra: test
Requires-Dist: ddt (>=1.3.1) ; extra == 'test'
Requires-Dist: pytest (>=5.4.1) ; extra == 'test'
Requires-Dist: mock (>=4.0.2) ; extra == 'test'
Requires-Dist: nbformat ; extra == 'test'
Requires-Dist: nbconvert ; extra == 'test'
